midi_neural_processor/__init__.py
midi_neural_processor/processor.py
midi_neural_processor-1.0.3.dist-info/METADATA
midi_neural_processor-1.0.3.dist-info/WHEEL
midi_neural_processor-1.0.3.dist-info/licenses/LICENSE
midi_neural_processor-1.0.3.dist-info/RECORD
