Metadata-Version: 2.3
Name: midi-neural-processor
Version: 1.0.3
Summary: Tokenize MIDI files for neural network processing
Project-URL: Repository, https://github.com/johacks/midi-neural-processor
Author-email: Kevin Yang <ykcha9@gmail.com>, Hao Hao Tan <helloharry66@gmail.com>, johacks <joaquinjimenezlc@gmail.com>
Maintainer-email: johacks <joaquinjimenezlc@gmail.com>
Keywords: midi,midi-processor,midi-tokenizer,music,neural,processor,tokenizer
Classifier: Development Status :: 5 - Production/Stable
Classifier: Intended Audience :: Developers
Classifier: License :: OSI Approved :: MIT License
Classifier: Programming Language :: Python :: 3
Classifier: Programming Language :: Python :: 3 :: Only
Classifier: Programming Language :: Python :: 3.8
Classifier: Programming Language :: Python :: 3.9
Classifier: Programming Language :: Python :: 3.10
Classifier: Programming Language :: Python :: 3.11
Classifier: Programming Language :: Python :: 3.12
Classifier: Programming Language :: Python :: 3.13
Classifier: Topic :: Software Development :: Libraries
Classifier: Topic :: Software Development :: Libraries :: Python Modules
Requires-Python: >=3.8
Requires-Dist: pretty-midi>=0.2.8
Requires-Dist: setuptools>=43.0.0
